lxa_iobus/__init__.py
lxa_iobus/canopen.py
lxa_iobus/network.py
lxa_iobus/cli/__init__.py
lxa_iobus/cli/lpc11xxcanisp_invoke.py
lxa_iobus/cli/lpc11xxcanisp_program.py
lxa_iobus/cli/optick.py
lxa_iobus/cli/server.py
lxa_iobus/lpc11xxcanisp/__init__.py
lxa_iobus/lpc11xxcanisp/can_isp.py
lxa_iobus/lpc11xxcanisp/firmware/__init__.py
lxa_iobus/lpc11xxcanisp/firmware/ethmux-S01.bin
lxa_iobus/lpc11xxcanisp/firmware/lxatac_can_io-t01.bin
lxa_iobus/lpc11xxcanisp/firmware/optick-t01.bin
lxa_iobus/lpc11xxcanisp/firmware/ptxtac-S03_CAN_GPIO.bin
lxa_iobus/lpc11xxcanisp/loader/__init__.py
lxa_iobus/lpc11xxcanisp/loader/reset.bin
lxa_iobus/lpc11xxcanisp/loader/soft_reset.bin
lxa_iobus/node/__init__.py
lxa_iobus/node/base_node.py
lxa_iobus/node/bus_node.py
lxa_iobus/node/object_directory.py
lxa_iobus/node/products.py
lxa_iobus/node/remote_node.py
lxa_iobus/server/__init__.py
lxa_iobus/server/server.py
lxa_iobus/server/static/index.html
lxa_iobus/server/static/main.js
lxa_iobus/server/static/style.css
lxa_iobus/server/static/lib/jquery-3.5.1.js
lxa_iobus/server/static/lib/jquery-3.5.1.min.js
lxa_iobus/server/static/lib/jquery-3.5.1.min.map
lxa_iobus/server/static/lib/pure-min.css
lxa_iobus/server/static/lib/ractive.js
lxa_iobus/server/static/lib/ractive.min.js
lxa_iobus/server/static/lib/ractive.min.js.map
lxa_iobus/server/static/lib/rpc.js
lxa_iobus-0.5.1.dist-info/LICENSE.txt
lxa_iobus-0.5.1.dist-info/METADATA
lxa_iobus-0.5.1.dist-info/WHEEL
lxa_iobus-0.5.1.dist-info/entry_points.txt
lxa_iobus-0.5.1.dist-info/top_level.txt
lxa_iobus-0.5.1.dist-info/RECORD
