Metadata-Version: 2.1
Name: lxa-iobus
Version: 0.5.1
Summary: Linux Automation IOBus Server
Author-email: Linux Automation GmbH <info@linux-automation.com>
License: Apache License
License-File: LICENSE.txt
Requires-Dist: aiohttp ~=3.8
Requires-Dist: aiohttp-json-rpc ==0.13.3
Requires-Dist: python-can
Requires-Dist: janus
